LICENSE
MANIFEST.in
README.rst
git-blackhole
git-blackhole-basic-usage.5
git-blackhole.1
git_blackhole.py
setup.py
git_blackhole.egg-info/PKG-INFO
git_blackhole.egg-info/SOURCES.txt
git_blackhole.egg-info/dependency_links.txt
git_blackhole.egg-info/entry_points.txt
git_blackhole.egg-info/top_level.txt