Metadata-Version: 1.1
Name: git-blackhole
Version: 0.1.0.post1
Summary: Continuous backup and recoverable trash can for Git
Home-page: https://github.com/tkf/git-blackhole
Author: Takafumi Arakaki
Author-email: aka.tkf@gmail.com
License: BSD-2-Clause
Keywords: Git,Backup,CLI
Platform: UNKNOWN
Classifier: Development Status :: 3 - Alpha
Classifier: License :: OSI Approved :: BSD License
Classifier: Programming Language :: Python :: 2.7
Classifier: Programming Language :: Python :: 3
Classifier: Topic :: Software Development :: Version Control :: Git
